<templateSet group="user">
  <template name="rem" value="// TODO den remove" description="" toReformat="false" toShortenFQNames="true">
    <context>
      <option name="GROOVY" value="true" />
      <option name="JAVA_CODE" value="true" />
      <option name="JAVA_SCRIPT" value="true" />
      <option name="KOTLIN" value="true" />
    </context>
  </template>
  <template name="in" value="== null" description="" toReformat="false" toShortenFQNames="true">
    <context>
      <option name="GROOVY" value="true" />
      <option name="JAVA_CODE" value="true" />
      <option name="JAVA_SCRIPT" value="true" />
      <option name="KOTLIN" value="true" />
    </context>
  </template>
  <template name="impl" value="// TODO den implement" description="" toReformat="false" toShortenFQNames="true">
    <context>
      <option name="GROOVY" value="true" />
      <option name="JAVA_CODE" value="true" />
      <option name="JAVA_SCRIPT" value="true" />
      <option name="KOTLIN" value="true" />
    </context>
  </template>
  <template name="doc" value="// TODO den add documentation" description="" toReformat="false" toShortenFQNames="true">
    <context>
      <option name="GROOVY" value="true" />
      <option name="JAVA_CODE" value="true" />
      <option name="JAVA_SCRIPT" value="true" />
      <option name="KOTLIN" value="true" />
    </context>
  </template>
  <template name="sf" value="String.format(&quot;$END$&quot;)" description="" toReformat="false" toShortenFQNames="true">
    <context>
      <option name="JAVA_CODE" value="true" />
    </context>
  </template>
</templateSet>